{"metadata":{},"options":{"plugins":[{"key":"base$1$0","visitor":{"_exploded":{},"_verified":{},"JSXNamespacedName":{"enter":[null]},"JSXElement":{"exit":[null]},"JSXFragment":{"exit":[null]},"Program":{"enter":[null],"exit":[null]},"JSXAttribute":{"enter":[null]}},"options":{"pragma":"React.createElement","pragmaFrag":"React.Fragment","throwIfNamespace":true,"useBuiltIns":false}},{"key":"base$1$1","visitor":{"ExportDefaultDeclaration":{"enter":[null]},"CallExpression":{"enter":[null]},"_exploded":true,"_verified":true},"options":{}},{"key":"base$0$0","visitor":{"Program":{"enter":[null]},"_exploded":true,"_verified":true},"options":{"generateLetDeclarations":true,"enforceStrictMode":false}},{"key":"base$0$1","visitor":{"_exploded":true,"_verified":true},"options":{}},{"key":"base$0$2","visitor":{"_exploded":{},"_verified":{},"Program":{"enter":[null]},"ImportDeclaration":{"enter":[null,null]},"ClassProperty":{"enter":[null]},"AssignmentPattern":{"enter":[null]},"TypeCastExpression":{"enter":[null,null]},"CallExpression":{"enter":[null]},"OptionalCallExpression":{"enter":[null]},"NewExpression":{"enter":[null]},"ImportSpecifier":{"enter":[null]},"ClassDeclaration":{"enter":[null]},"ClassExpression":{"enter":[null]},"FunctionDeclaration":{"enter":[null]},"FunctionExpression":{"enter":[null]},"ObjectMethod":{"enter":[null]},"ArrowFunctionExpression":{"enter":[null]},"ClassMethod":{"enter":[null]},"AnyTypeAnnotation":{"enter":[null]},"ArrayTypeAnnotation":{"enter":[null]},"BooleanTypeAnnotation":{"enter":[null]},"BooleanLiteralTypeAnnotation":{"enter":[null]},"NullLiteralTypeAnnotation":{"enter":[null]},"ClassImplements":{"enter":[null]},"DeclareClass":{"enter":[null]},"DeclareFunction":{"enter":[null]},"DeclareInterface":{"enter":[null]},"DeclareModule":{"enter":[null]},"DeclareModuleExports":{"enter":[null]},"DeclareTypeAlias":{"enter":[null]},"DeclareOpaqueType":{"enter":[null]},"DeclareVariable":{"enter":[null]},"DeclareExportDeclaration":{"enter":[null]},"DeclareExportAllDeclaration":{"enter":[null]},"DeclaredPredicate":{"enter":[null]},"ExistsTypeAnnotation":{"enter":[null]},"FunctionTypeAnnotation":{"enter":[null]},"FunctionTypeParam":{"enter":[null]},"GenericTypeAnnotation":{"enter":[null]},"InferredPredicate":{"enter":[null]},"InterfaceExtends":{"enter":[null]},"InterfaceDeclaration":{"enter":[null]},"InterfaceTypeAnnotation":{"enter":[null]},"IntersectionTypeAnnotation":{"enter":[null]},"MixedTypeAnnotation":{"enter":[null]},"EmptyTypeAnnotation":{"enter":[null]},"NullableTypeAnnotation":{"enter":[null]},"NumberLiteralTypeAnnotation":{"enter":[null]},"NumberTypeAnnotation":{"enter":[null]},"ObjectTypeAnnotation":{"enter":[null]},"ObjectTypeInternalSlot":{"enter":[null]},"ObjectTypeCallProperty":{"enter":[null]},"ObjectTypeIndexer":{"enter":[null]},"ObjectTypeProperty":{"enter":[null]},"ObjectTypeSpreadProperty":{"enter":[null]},"OpaqueType":{"enter":[null]},"QualifiedTypeIdentifier":{"enter":[null]},"StringLiteralTypeAnnotation":{"enter":[null]},"StringTypeAnnotation":{"enter":[null]},"ThisTypeAnnotation":{"enter":[null]},"TupleTypeAnnotation":{"enter":[null]},"TypeofTypeAnnotation":{"enter":[null]},"TypeAlias":{"enter":[null]},"TypeAnnotation":{"enter":[null]},"TypeParameter":{"enter":[null]},"TypeParameterDeclaration":{"enter":[null]},"TypeParameterInstantiation":{"enter":[null]},"UnionTypeAnnotation":{"enter":[null]},"Variance":{"enter":[null]},"VoidTypeAnnotation":{"enter":[null]},"ExportAllDeclaration":{"enter":[null]},"ExportDefaultDeclaration":{"enter":[null]},"ExportNamedDeclaration":{"enter":[null]}},"options":{}},{"key":"base$0$3","visitor":{"CallExpression":{"enter":[null]},"BinaryExpression":{"enter":[null]},"MemberExpression":{"enter":[null],"exit":[null]},"_exploded":true,"_verified":true,"Identifier":{"enter":[null]},"JSXIdentifier":{"enter":[null]}},"options":{"polyfill":false,"useBuiltIns":true}},{"key":"base$0$4","visitor":{"_exploded":true,"_verified":true},"options":{}},{"key":"base$0$5","visitor":{"_exploded":{},"_verified":{},"VariableDeclarator":{"enter":[null]},"ExportNamedDeclaration":{"enter":[null]},"CatchClause":{"enter":[null]},"AssignmentExpression":{"enter":[null]},"ObjectExpression":{"enter":[null]},"FunctionDeclaration":{"enter":[null]},"FunctionExpression":{"enter":[null]},"ObjectMethod":{"enter":[null]},"ArrowFunctionExpression":{"enter":[null]},"ClassMethod":{"enter":[null]},"ForInStatement":{"enter":[null]},"ForOfStatement":{"enter":[null]}},"options":{}},{"key":"transform-meteor-async-await","visitor":{"AwaitExpression":{"enter":[null]},"_exploded":true,"_verified":true,"FunctionDeclaration":{"exit":[null]},"FunctionExpression":{"exit":[null]},"ObjectMethod":{"exit":[null]},"ArrowFunctionExpression":{"exit":[null]},"ClassMethod":{"exit":[null]}},"options":{"useNativeAsyncAwait":false}},{"key":"transform-meteor-dynamic-import","visitor":{"_exploded":{},"_verified":{},"CallExpression":{"enter":[null]}},"options":{}},{"key":"base$0$8","visitor":{"_exploded":{},"_verified":{},"Program":{"enter":[null]}},"options":{}},{"key":"base$0$9","visitor":{"Program":{"exit":[null]},"_exploded":true,"_verified":true},"options":{"allowTopLevelThis":true,"strictMode":false,"loose":true}},{"key":"base$0$10","visitor":{"_exploded":{},"_verified":{},"PrivateName":{"enter":[null]},"ClassDeclaration":{"enter":[null]},"ClassExpression":{"enter":[null]}},"options":{"loose":true}}],"compact":false,"ast":true,"babelrc":false,"configFile":false,"parserOpts":{"sourceType":"module","sourceFileName":"imports/ui/pages/architecture.js","plugins":["*","flow","jsx","asyncGenerators","bigInt","classPrivateMethods","classPrivateProperties","classProperties","doExpressions","dynamicImport","exportDefaultFrom","exportExtensions","exportNamespaceFrom","functionBind","functionSent","importMeta","nullishCoalescingOperator","numericSeparator","objectRestSpread","optionalCatchBinding","optionalChaining","pipelineOperator","throwExpressions","jsx",["flow",{}],["flow",{}],"objectRestSpread","objectRestSpread","dynamicImport","asyncGenerators","classProperties","classPrivateProperties"],"allowImportExportEverywhere":true,"allowReturnOutsideFunction":true,"strictMode":false},"sourceFileName":"imports/ui/pages/architecture.js","filename":"imports/ui/pages/architecture.js","sourceMaps":true,"passPerPreset":false,"envName":"development","cwd":"/home/martijn/Documents/GitHub/QRSMeteor","root":"/home/martijn/Documents/GitHub/QRSMeteor","presets":[],"generatorOpts":{"filename":"imports/ui/pages/architecture.js","comments":true,"compact":false,"sourceMaps":true,"sourceFileName":"imports/ui/pages/architecture.js"}},"code":"let Template;\nmodule.watch(require(\"meteor/templating\"), {\n  Template(v) {\n    Template = v;\n  }\n\n}, 0);\nlet Session;\nmodule.watch(require(\"meteor/session\"), {\n  Session(v) {\n    Session = v;\n  }\n\n}, 1);\nmodule.watch(require(\"/imports/ui/UIHelpers\"));\nlet APILogs;\nmodule.watch(require(\"/imports/api/APILogs\"), {\n  APILogs(v) {\n    APILogs = v;\n  }\n\n}, 2);\nTemplate.introductionSecurity.events({\n  'click .mindMapSecurity'() {\n    $('.ui.modal.mindMapSecurity').modal('show');\n  },\n\n  'click .integratedFlowModal'() {\n    $('.ui.modal.integratedFlowModal').modal('show');\n  }\n\n});\nTemplate.introductionSecurity.onRendered(function () {\n  Template.instance().$('.ui.embed').embed();\n  Template.instance().$('.ui.accordion').accordion({\n    exclusive: false\n  });\n});\nTemplate.architecture.onRendered(function () {\n  Template.instance().$('.ui.embed').embed();\n});\nTemplate.introductionArchitecturePage.onRendered(function () {\n  Template.instance().$('.ui.accordion').accordion({\n    exclusive: false\n  });\n});","map":{"version":3,"sources":["imports/ui/pages/architecture.js"],"names":["Template","module","watch","require","v","Session","APILogs","introductionSecurity","events","$","modal","onRendered","instance","embed","accordion","exclusive","architecture","introductionArchitecturePage"],"mappings":"AAAA,IAAIA,QAAJ;AAAaC,OAAOC,KAAP,CAAaC,QAAQ,mBAAR,CAAb,EAA0C;AAACH,WAASI,CAAT,EAAW;AAACJ,eAASI,CAAT;AAAW;;AAAxB,CAA1C,EAAoE,CAApE;AAAuE,IAAIC,OAAJ;AAAYJ,OAAOC,KAAP,CAAaC,QAAQ,gBAAR,CAAb,EAAuC;AAACE,UAAQD,CAAR,EAAU;AAACC,cAAQD,CAAR;AAAU;;AAAtB,CAAvC,EAA+D,CAA/D;AAAkEH,OAAOC,KAAP,CAAaC,QAAQ,uBAAR,CAAb;AAA+C,IAAIG,OAAJ;AAAYL,OAAOC,KAAP,CAAaC,QAAQ,sBAAR,CAAb,EAA6C;AAACG,UAAQF,CAAR,EAAU;AAACE,cAAQF,CAAR;AAAU;;AAAtB,CAA7C,EAAqE,CAArE;AAM7NJ,SAASO,oBAAT,CAA8BC,MAA9B,CAAqC;AACjC,6BAA4B;AACxBC,MAAE,2BAAF,EACKC,KADL,CACW,MADX;AAEH,GAJgC;;AAKjC,iCAAgC;AAC5BD,MAAE,+BAAF,EACKC,KADL,CACW,MADX;AAEH;;AARgC,CAArC;AAWAV,SAASO,oBAAT,CAA8BI,UAA9B,CAAyC,YAAW;AAChDX,WAASY,QAAT,GACKH,CADL,CACO,WADP,EAEKI,KAFL;AAIAb,WAASY,QAAT,GACKH,CADL,CACO,eADP,EAEKK,SAFL,CAEe;AAAEC,eAAW;AAAb,GAFf;AAIH,CATD;AAWAf,SAASgB,YAAT,CAAsBL,UAAtB,CAAiC,YAAW;AACxCX,WAASY,QAAT,GACKH,CADL,CACO,WADP,EAEKI,KAFL;AAGH,CAJD;AAMAb,SAASiB,4BAAT,CAAsCN,UAAtC,CAAiD,YAAW;AAExDX,WAASY,QAAT,GACKH,CADL,CACO,eADP,EAEKK,SAFL,CAEe;AAAEC,eAAW;AAAb,GAFf;AAGH,CALD","sourcesContent":["\nimport { Template } from 'meteor/templating';\nimport { Session } from 'meteor/session';\nimport '/imports/ui/UIHelpers';\nimport { APILogs } from '/imports/api/APILogs';\n\nTemplate.introductionSecurity.events({\n    'click .mindMapSecurity' () {\n        $('.ui.modal.mindMapSecurity')\n            .modal('show');\n    },\n    'click .integratedFlowModal' () {\n        $('.ui.modal.integratedFlowModal')\n            .modal('show');\n    }\n})\n\nTemplate.introductionSecurity.onRendered(function() {\n    Template.instance()\n        .$('.ui.embed')\n        .embed();\n\n    Template.instance()\n        .$('.ui.accordion')\n        .accordion({ exclusive: false });\n\n})\n\nTemplate.architecture.onRendered(function() {\n    Template.instance()\n        .$('.ui.embed')\n        .embed();\n})\n\nTemplate.introductionArchitecturePage.onRendered(function() {\n\n    Template.instance()\n        .$('.ui.accordion')\n        .accordion({ exclusive: false });\n})\n"]},"sourceType":"script","hash":"bbe38553d49e53a2d03cff4d399907efc5240f5f"}
