[
  {
    "id": "111c3a98-661c-4644-86b0-932c193bd1fb",
    "createdDate": "2017-09-26T13:29:15.534Z",
    "modifiedDate": "2017-09-26T13:29:15.534Z",
    "modifiedByUserName": "QLIK-AB0Q2URN5T\\qlikexternal",
    "name": "customer",
    "valueType": "Text",
    "choiceValues": [
      "Orn LLC",
      "Abbott Group",
      "Spinka Group"
    ],
    "objectTypes": [
      "App",
      "ContentLibrary",
      "DataConnection",
      "ReloadTask",
      "Stream",
      "User"
    ],
    "privileges": null,
    "impactSecurityAccess": false,
    "schemaPath": "CustomPropertyDefinition"
  }
]