[
  {
    "id": "429c1753-aff7-4bfe-9a41-270d23836169",
    "createdDate": "2017-09-20T13:27:06.789Z",
    "modifiedDate": "2017-09-20T13:27:06.789Z",
    "modifiedByUserName": "QLIK-AB0Q2URN5T\\qlikexternal",
    "name": "customers",
    "valueType": "Text",
    "choiceValues": [
      "Gerhold Inc",
      "Dietrich Group",
      "Volkman and Sons"
    ],
    "objectTypes": [
      "App",
      "ContentLibrary",
      "DataConnection",
      "ReloadTask",
      "Stream",
      "User"
    ],
    "privileges": null,
    "impactSecurityAccess": false,
    "schemaPath": "CustomPropertyDefinition"
  }
]